setup.py
infusionsoft/__init__.py
infusionsoft/client.py
infusionsoft.egg-info/PKG-INFO
infusionsoft.egg-info/SOURCES.txt
infusionsoft.egg-info/dependency_links.txt
infusionsoft.egg-info/requires.txt
infusionsoft.egg-info/top_level.txt