Metadata-Version: 1.1
Name: infusionsoft
Version: 0.1.1
Summary: A client library for the InfusionSoft API
Home-page: https://github.com/realgeeks/infusionsoft
Author: Kevin McCarthy
Author-email: me@kevinmccarthy.org
License: MIT
Keywords: infusionsoft client api
Platform: UNKNOWN
Classifier: Development Status :: 3 - Alpha
Classifier: Intended Audience :: Developers
Classifier: License :: OSI Approved :: MIT License
Classifier: Programming Language :: Python :: 2.7
